coucou/__init__.py
coucou/base.py
coucou/routing/__init__.py
coucou/routing/tsp/__init__.py
coucou/routing/tsp/nlkh.py
coucou-0.1.0.dist-info/LICENSE
coucou-0.1.0.dist-info/WHEEL
coucou-0.1.0.dist-info/METADATA
coucou-0.1.0.dist-info/RECORD
