Metadata-Version: 2.1
Name: coucou
Version: 0.1.0
Summary: 
License: MIT
Author: Mehdi Zouitine
Author-email: mehdizouitinegm@gmail.com
Requires-Python: >=3.9,<4.0
Classifier: License :: OSI Approved :: MIT License
Classifier: Programming Language :: Python :: 3
Classifier: Programming Language :: Python :: 3.9
Classifier: Programming Language :: Python :: 3.10
Requires-Dist: ruff (>=0.0.57,<0.0.58)
